roman_cuts/__init__.py
roman_cuts/cube.py
roman_cuts/data/wcs/Roman_WFI_wcs_field003_sca02_F087.json.bz2
roman_cuts/data/wcs/Roman_WFI_wcs_field003_sca02_F146.json.bz2
roman_cuts/data/wcs/Roman_WFI_wcs_field003_sca02_F213.json.bz2
roman_cuts/data/wcs/Roman_WFI_wcss_field003_sca02_F087.json.bz2
roman_cuts/data/wcs/Roman_WFI_wcss_field003_sca02_F146.json.bz2
roman_cuts/data/wcs/Roman_WFI_wcss_field003_sca02_F213.json.bz2
roman_cuts/utils.py
roman_cuts-0.3.1.dist-info/METADATA
roman_cuts-0.3.1.dist-info/WHEEL
roman_cuts-0.3.1.dist-info/licenses/LICENCE
roman_cuts-0.3.1.dist-info/RECORD
