Metadata-Version: 2.4
Name: roman-cuts
Version: 0.3.1
Summary: 
License-File: LICENCE
Author: Jorge Martinez-Palomera
Author-email: jorgemarpa@ug.uchile.cl
Requires-Python: >=3.10,<4.0
Classifier: Programming Language :: Python :: 3
Classifier: Programming Language :: Python :: 3.10
Classifier: Programming Language :: Python :: 3.11
Classifier: Programming Language :: Python :: 3.12
Classifier: Programming Language :: Python :: 3.13
Classifier: Programming Language :: Python :: 3.14
Requires-Dist: asdf-astropy (>=0.7)
Requires-Dist: astropy (>5,<7)
Requires-Dist: matplotlib (>=3.10.1,<4.0.0)
Requires-Dist: numpy (>1.26,<3.0)
Requires-Dist: pandas (>1.5,<3.0)
Requires-Dist: tqdm (>=4.67.1,<5.0.0)
